thaipackage/__init__.py
thaipackage/blank_func.py
thaipackage/main.py
thaipackge-0.1.0.dist-info/LICENSE
thaipackge-0.1.0.dist-info/METADATA
thaipackge-0.1.0.dist-info/WHEEL
thaipackge-0.1.0.dist-info/entry_points.txt
thaipackge-0.1.0.dist-info/top_level.txt
thaipackge-0.1.0.dist-info/RECORD
