Metadata-Version: 2.1
Name: thaipackge
Version: 0.1.0
Summary: A thaipackge / template for creating a new Python package
Home-page: https://github.com/nhithai4620/create_lib_demo1
Author: thai-info
Author-email: nguyenhithai4620@gmail.com
Maintainer: thia-info
Maintainer-email: nguyenhithai4620@gmail.com
License: MIT
Download-URL: https://github.com/nhithai4620/create_lib_demo1/tarball/master
Platform: UNKNOWN
Classifier: Development Status :: 4 - Beta
Classifier: License :: OSI Approved :: MIT License
Classifier: Topic :: Software Development :: Libraries :: Python Modules
Classifier: Intended Audience :: Developers
Classifier: Programming Language :: Python :: 2
Classifier: Programming Language :: Python :: 2.7
Classifier: Programming Language :: Python :: 3
Classifier: Programming Language :: Python :: 3.5
Classifier: Programming Language :: Python :: 3.6
Classifier: Programming Language :: Python :: 3.7
Classifier: Programming Language :: Python :: Implementation
Requires-Python: !=3.0.*,!=3.1.*,!=3.2.*,!=3.3.*,!=3.4.*,<4,>=2.7
